<?xml version="1.0" encoding="UTF-8"?>
<adapt_framework>
    <bundle>
        <name>guzzlehttp_psr7</name>
        <label>Guzzle PSR7</label>
        <type>extension</type>
        <version>1.3.1</version>
        <namespace>\GuzzleHttp\Psr7</namespace>
        <version_status>release</version_status>
        <availability>public</availability>
        <depends_on>
            <bundle>
                <name>adapt</name>
                <version>2</version>
            </bundle>
            <bundle>
                <name>psr_http_message</name>
                <version>1</version>
            </bundle>
            <bundle>
                <name>vendor</name>
            </bundle>
        </depends_on>
    </bundle>
</adapt_framework>
